README.rst
setup.cfg
setup.py
appcheck/__init__.py
appcheck/appcheck.py
appcheck/cli.py
appcheck/config.py
appcheck/exceptions.py
appcheck/utils.py
appcheck.egg-info/PKG-INFO
appcheck.egg-info/SOURCES.txt
appcheck.egg-info/dependency_links.txt
appcheck.egg-info/entry_points.txt
appcheck.egg-info/not-zip-safe
appcheck.egg-info/requires.txt
appcheck.egg-info/top_level.txt