Metadata-Version: 1.1
Name: appcheck
Version: 0.1.5
Summary: Codenomicon Appcheck command line tools and API client
Home-page: https://bitbucket.org/codenomicon/appcheck-cli
Author: Joonas Kuorilehto
Author-email: joonas.kuorilehto@codenomicon.com
License: UNKNOWN
Platform: UNKNOWN
Classifier: Development Status :: 4 - Beta
Classifier: Environment :: Console
Classifier: License :: OSI Approved :: MIT License
Classifier: Operating System :: OS Independent
Classifier: Programming Language :: Python
Classifier: Programming Language :: Python :: 2
Classifier: Programming Language :: Python :: 2.7
Classifier: Programming Language :: Python :: 3
Classifier: Programming Language :: Python :: 3.4
Classifier: Topic :: Security
Classifier: Topic :: Software Development
Classifier: Topic :: Software Development :: Libraries
Classifier: Topic :: Utilities
